setup.py
mongogogo/__init__.py
mongogogo/cursor.py
mongogogo/record.py
mongogogo.egg-info/PKG-INFO
mongogogo.egg-info/SOURCES.txt
mongogogo.egg-info/dependency_links.txt
mongogogo.egg-info/entry_points.txt
mongogogo.egg-info/not-zip-safe
mongogogo.egg-info/requires.txt
mongogogo.egg-info/top_level.txt
mongogogo/query/__init__.py
mongogogo/schema/__init__.py
mongogogo/schema/filters.py
mongogogo/schema/nodes.py
mongogogo/schema/utils.py
mongogogo/schema/tests/__init__.py
mongogogo/schema/tests/conftest.py
mongogogo/schema/tests/test_deserialize_to_class.py
mongogogo/schema/tests/test_mapping.py
mongogogo/schema/tests/test_string.py
mongogogo/schema/tests/test_types.py
mongogogo/tests/__init__.py
mongogogo/tests/conftest.py
mongogogo/tests/test_basics.py
mongogogo/tests/test_subdict.py