Metadata-Version: 1.0
Name: mongogogo
Version: 1.0
Summary: Mongo Schema and Query Library
Home-page: UNKNOWN
Author: COM.lounge
Author-email: info@comlounge.net
License: MIT
Platform: UNKNOWN
